MANIFEST.in
README.md
jeda.json
setup.cfg
setup.py
jeda/__init__.py
jeda/_version.py
jeda/jeda.py
jeda.egg-info/PKG-INFO
jeda.egg-info/SOURCES.txt
jeda.egg-info/dependency_links.txt
jeda.egg-info/not-zip-safe
jeda.egg-info/requires.txt
jeda.egg-info/top_level.txt
jeda/static/extension.js
jeda/static/index.html
jeda/static/index.js
jeda/static/index.js.map